erc7730/__init__.py
erc7730/common/abi.py
erc7730/common/binary.py
erc7730/common/client.py
erc7730/common/json.py
erc7730/common/ledger.py
erc7730/common/options.py
erc7730/common/output.py
erc7730/common/properties.py
erc7730/common/pydantic.py
erc7730/convert/__init__.py
erc7730/convert/calldata/__init__.py
erc7730/convert/calldata/convert_erc7730_input_to_calldata.py
erc7730/convert/calldata/v1/__init__.py
erc7730/convert/calldata/v1/abi.py
erc7730/convert/calldata/v1/descriptor.py
erc7730/convert/calldata/v1/enum.py
erc7730/convert/calldata/v1/field.py
erc7730/convert/calldata/v1/path.py
erc7730/convert/calldata/v1/selector.py
erc7730/convert/calldata/v1/tlv.py
erc7730/convert/convert.py
erc7730/convert/ledger/__init__.py
erc7730/convert/ledger/eip712/__init__.py
erc7730/convert/ledger/eip712/convert_eip712_to_erc7730.py
erc7730/convert/ledger/eip712/convert_erc7730_to_eip712.py
erc7730/convert/resolved/__init__.py
erc7730/convert/resolved/constants.py
erc7730/convert/resolved/convert_erc7730_input_to_resolved.py
erc7730/convert/resolved/enums.py
erc7730/convert/resolved/parameters.py
erc7730/convert/resolved/references.py
erc7730/convert/resolved/values.py
erc7730/format/__init__.py
erc7730/format/format.py
erc7730/generate/__init__.py
erc7730/generate/generate.py
erc7730/generate/schema_tree.py
erc7730/lint/__init__.py
erc7730/lint/classifier/__init__.py
erc7730/lint/classifier/abi_classifier.py
erc7730/lint/classifier/eip712_classifier.py
erc7730/lint/lint.py
erc7730/lint/lint_base.py
erc7730/lint/lint_transaction_type_classifier.py
erc7730/lint/lint_validate_abi.py
erc7730/lint/lint_validate_display_fields.py
erc7730/lint/lint_validate_max_length.py
erc7730/list/__init__.py
erc7730/list/list.py
erc7730/main.py
erc7730/model/__init__.py
erc7730/model/abi.py
erc7730/model/base.py
erc7730/model/calldata/__init__.py
erc7730/model/calldata/descriptor.py
erc7730/model/calldata/types.py
erc7730/model/calldata/v1/__init__.py
erc7730/model/calldata/v1/descriptor.py
erc7730-0.5.7.dist-info/entry_points.txt
erc7730-0.5.7.dist-info/WHEEL
erc7730-0.5.7.dist-info/METADATA
erc7730-0.5.7.dist-info/licenses/LICENSE
erc7730-0.5.7.dist-info/RECORD
